{
  "hash": "b8561acd",
  "browserHash": "2e06d773",
  "optimized": {
    "querystring": {
      "src": "../../node_modules/querystring/index.js",
      "file": "querystring.js",
      "fileHash": "bf54ed30",
      "needsInterop": true
    },
    "axios": {
      "src": "../../node_modules/axios/index.js",
      "file": "axios.js",
      "fileHash": "a8d03644",
      "needsInterop": false
    },
    "linq": {
      "src": "../../node_modules/linq/linq.js",
      "file": "linq.js",
      "fileHash": "47deddd0",
      "needsInterop": false
    }
  },
  "chunks": {
    "chunk-TQKZRU5K": {
      "file": "chunk-TQKZRU5K.js"
    }
  }
}